README.rst
setup.cfg
setup.py
compress_storage/__init__.py
compress_storage/base.py
compress_storage/fieldfiles.py
compress_storage/models.py
compress_storage/tasks.py
django_compress_storage.egg-info/PKG-INFO
django_compress_storage.egg-info/SOURCES.txt
django_compress_storage.egg-info/dependency_links.txt
django_compress_storage.egg-info/requires.txt
django_compress_storage.egg-info/top_level.txt