Metadata-Version: 1.1
Name: django-compress-storage
Version: 0.9.1
Summary: Automantic compress files after upload
Home-page: https://github.com/valdergallo/django-compress-storage
Author: valdergallo
Author-email: valdergallo@gmail.com
License: FREEBSD
Download-URL: https://github.com/valdergallo/django-compress-storage/tarball/v0.9.1/
Keywords: django,compress,field,zip,tar,gzip
Platform: UNKNOWN
Classifier: Framework :: Django
Classifier: Operating System :: OS Independent
Classifier: Topic :: Utilities
Classifier: Programming Language :: Python
Classifier: Programming Language :: Python :: 2.6
Classifier: Programming Language :: Python :: 2.7
Classifier: Programming Language :: Python :: 3.3
